[
  {
    "result": "cloak_makeshift_sheet",
    "type": "recipe",
    "activity_level": "LIGHT_EXERCISE",
    "category": "CC_ARMOR",
    "subcategory": "CSC_ARMOR_SUIT",
    "skill_used": "tailor",
    "time": "1 m",
    "reversible": true,
    "autolearn": true,
    "components": [ [ [ "sheet", 1 ] ], [ [ "nail", 1 ], [ "splinter", 1 ], [ "skewer_bone", 1 ] ] ]
  },
  {
    "result": "cloak_makeshift_blanket",
    "type": "recipe",
    "activity_level": "LIGHT_EXERCISE",
    "category": "CC_ARMOR",
    "subcategory": "CSC_ARMOR_SUIT",
    "skill_used": "tailor",
    "time": "1 m",
    "reversible": true,
    "autolearn": true,
    "components": [ [ [ "blanket", 1 ] ], [ [ "nail", 1 ], [ "splinter", 1 ], [ "skewer_bone", 1 ] ] ]
  },
  {
    "result": "cloak_makeshift_down_blanket",
    "type": "recipe",
    "activity_level": "LIGHT_EXERCISE",
    "category": "CC_ARMOR",
    "subcategory": "CSC_ARMOR_SUIT",
    "skill_used": "tailor",
    "time": "1 m",
    "reversible": true,
    "autolearn": true,
    "components": [ [ [ "down_blanket", 1 ] ], [ [ "nail", 1 ], [ "splinter", 1 ], [ "skewer_bone", 1 ] ] ]
  },
  {
    "result": "cloak_makeshift_fur_blanket",
    "type": "recipe",
    "activity_level": "LIGHT_EXERCISE",
    "category": "CC_ARMOR",
    "subcategory": "CSC_ARMOR_SUIT",
    "skill_used": "tailor",
    "time": "1 m",
    "reversible": true,
    "autolearn": true,
    "components": [ [ [ "fur_blanket", 1 ] ], [ [ "nail", 1 ], [ "splinter", 1 ], [ "skewer_bone", 1 ] ] ]
  }
]
